{
    "description": "",
    "tags": [],
    "size": {
        "height": 853,
        "width": 853
    },
    "objects": [
        {
            "id": 1741389,
            "classId": 4131,
            "description": "",
            "geometryType": "polygon",
            "labelerLogin": "az@datasetninja.com",
            "createdAt": "2023-06-07T14:13:32.227Z",
            "updatedAt": "2023-06-07T14:13:32.227Z",
            "tags": [],
            "classTitle": "croissant",
            "points": {
                "exterior": [
                    [
                        677,
                        764
                    ],
                    [
                        576,
                        764
                    ],
                    [
                        575,
                        763
                    ],
                    [
                        559,
                        763
                    ],
                    [
                        558,
                        762
                    ],
                    [
                        549,
                        762
                    ],
                    [
                        548,
                        761
                    ],
                    [
                        542,
                        761
                    ],
                    [
                        541,
                        760
                    ],
                    [
                        539,
                        760
                    ],
                    [
                        538,
                        759
                    ],
                    [
                        537,
                        759
                    ],
                    [
                        536,
                        758
                    ],
                    [
                        535,
                        758
                    ],
                    [
                        533,
                        756
                    ],
                    [
                        532,
                        756
                    ],
                    [
                        530,
                        754
                    ],
                    [
                        529,
                        754
                    ],
                    [
                        528,
                        754
                    ],
                    [
                        528,
                        753
                    ],
                    [
                        526,
                        751
                    ],
                    [
                        526,
                        750
                    ],
                    [
                        524,
                        748
                    ],
                    [
                        524,
                        747
                    ],
                    [
                        521,
                        744
                    ],
                    [
                        521,
                        743
                    ],
                    [
                        510,
                        732
                    ],
                    [
                        510,
                        731
                    ],
                    [
                        506,
                        727
                    ],
                    [
                        506,
                        726
                    ],
                    [
                        504,
                        724
                    ],
                    [
                        504,
                        723
                    ],
                    [
                        502,
                        721
                    ],
                    [
                        502,
                        720
                    ],
                    [
                        501,
                        719
                    ],
                    [
                        501,
                        718
                    ],
                    [
                        500,
                        717
                    ],
                    [
                        500,
                        716
                    ],
                    [
                        498,
                        714
                    ],
                    [
                        498,
                        713
                    ],
                    [
                        497,
                        712
                    ],
                    [
                        497,
                        710
                    ],
                    [
                        495,
                        708
                    ],
                    [
                        495,
                        707
                    ],
                    [
                        494,
                        706
                    ],
                    [
                        494,
                        705
                    ],
                    [
                        493,
                        704
                    ],
                    [
                        493,
                        703
                    ],
                    [
                        490,
                        700
                    ],
                    [
                        490,
                        699
                    ],
                    [
                        483,
                        692
                    ],
                    [
                        483,
                        691
                    ],
                    [
                        481,
                        689
                    ],
                    [
                        481,
                        688
                    ],
                    [
                        479,
                        686
                    ],
                    [
                        479,
                        685
                    ],
                    [
                        477,
                        683
                    ],
                    [
                        477,
                        682
                    ],
                    [
                        476,
                        681
                    ],
                    [
                        476,
                        680
                    ],
                    [
                        475,
                        679
                    ],
                    [
                        475,
                        678
                    ],
                    [
                        474,
                        677
                    ],
                    [
                        474,
                        676
                    ],
                    [
                        473,
                        675
                    ],
                    [
                        473,
                        673
                    ],
                    [
                        472,
                        672
                    ],
                    [
                        472,
                        671
                    ],
                    [
                        471,
                        670
                    ],
                    [
                        471,
                        668
                    ],
                    [
                        470,
                        667
                    ],
                    [
                        470,
                        665
                    ],
                    [
                        469,
                        664
                    ],
                    [
                        469,
                        662
                    ],
                    [
                        468,
                        661
                    ],
                    [
                        468,
                        659
                    ],
                    [
                        467,
                        658
                    ],
                    [
                        467,
                        657
                    ],
                    [
                        466,
                        656
                    ],
                    [
                        466,
                        654
                    ],
                    [
                        465,
                        653
                    ],
                    [
                        465,
                        652
                    ],
                    [
                        464,
                        651
                    ],
                    [
                        464,
                        650
                    ],
                    [
                        463,
                        649
                    ],
                    [
                        463,
                        648
                    ],
                    [
                        461,
                        646
                    ],
                    [
                        461,
                        645
                    ],
                    [
                        456,
                        640
                    ],
                    [
                        456,
                        639
                    ],
                    [
                        453,
                        636
                    ],
                    [
                        453,
                        635
                    ],
                    [
                        451,
                        633
                    ],
                    [
                        451,
                        632
                    ],
                    [
                        449,
                        630
                    ],
                    [
                        449,
                        629
                    ],
                    [
                        448,
                        628
                    ],
                    [
                        448,
                        627
                    ],
                    [
                        447,
                        626
                    ],
                    [
                        447,
                        625
                    ],
                    [
                        446,
                        624
                    ],
                    [
                        446,
                        622
                    ],
                    [
                        445,
                        621
                    ],
                    [
                        445,
                        619
                    ],
                    [
                        444,
                        618
                    ],
                    [
                        444,
                        616
                    ],
                    [
                        443,
                        615
                    ],
                    [
                        443,
                        612
                    ],
                    [
                        442,
                        611
                    ],
                    [
                        442,
                        609
                    ],
                    [
                        441,
                        608
                    ],
                    [
                        441,
                        605
                    ],
                    [
                        440,
                        604
                    ],
                    [
                        440,
                        603
                    ],
                    [
                        439,
                        602
                    ],
                    [
                        439,
                        601
                    ],
                    [
                        438,
                        600
                    ],
                    [
                        438,
                        599
                    ],
                    [
                        437,
                        598
                    ],
                    [
                        437,
                        597
                    ],
                    [
                        436,
                        596
                    ],
                    [
                        436,
                        595
                    ],
                    [
                        434,
                        593
                    ],
                    [
                        434,
                        592
                    ],
                    [
                        432,
                        590
                    ],
                    [
                        432,
                        589
                    ],
                    [
                        430,
                        586
                    ],
                    [
                        429,
                        586
                    ],
                    [
                        423,
                        580
                    ],
                    [
                        422,
                        580
                    ],
                    [
                        421,
                        579
                    ],
                    [
                        420,
                        579
                    ],
                    [
                        418,
                        577
                    ],
                    [
                        417,
                        577
                    ],
                    [
                        416,
                        576
                    ],
                    [
                        415,
                        576
                    ],
                    [
                        414,
                        575
                    ],
                    [
                        412,
                        575
                    ],
                    [
                        411,
                        574
                    ],
                    [
                        410,
                        574
                    ],
                    [
                        409,
                        573
                    ],
                    [
                        407,
                        573
                    ],
                    [
                        406,
                        572
                    ],
                    [
                        404,
                        572
                    ],
                    [
                        403,
                        571
                    ],
                    [
                        402,
                        572
                    ],
                    [
                        392,
                        572
                    ],
                    [
                        391,
                        573
                    ],
                    [
                        382,
                        573
                    ],
                    [
                        381,
                        574
                    ],
                    [
                        345,
                        574
                    ],
                    [
                        344,
                        573
                    ],
                    [
                        337,
                        573
                    ],
                    [
                        336,
                        572
                    ],
                    [
                        330,
                        572
                    ],
                    [
                        329,
                        571
                    ],
                    [
                        323,
                        571
                    ],
                    [
                        322,
                        570
                    ],
                    [
                        318,
                        570
                    ],
                    [
                        317,
                        569
                    ],
                    [
                        313,
                        569
                    ],
                    [
                        312,
                        568
                    ],
                    [
                        309,
                        568
                    ],
                    [
                        308,
                        567
                    ],
                    [
                        305,
                        567
                    ],
                    [
                        304,
                        566
                    ],
                    [
                        301,
                        566
                    ],
                    [
                        300,
                        565
                    ],
                    [
                        298,
                        565
                    ],
                    [
                        297,
                        564
                    ],
                    [
                        295,
                        564
                    ],
                    [
                        294,
                        563
                    ],
                    [
                        289,
                        563
                    ],
                    [
                        288,
                        564
                    ],
                    [
                        284,
                        564
                    ],
                    [
                        283,
                        565
                    ],
                    [
                        278,
                        565
                    ],
                    [
                        277,
                        566
                    ],
                    [
                        272,
                        566
                    ],
                    [
                        271,
                        567
                    ],
                    [
                        266,
                        567
                    ],
                    [
                        265,
                        568
                    ],
                    [
                        264,
                        568
                    ],
                    [
                        263,
                        569
                    ],
                    [
                        262,
                        569
                    ],
                    [
                        259,
                        572
                    ],
                    [
                        258,
                        572
                    ],
                    [
                        248,
                        582
                    ],
                    [
                        248,
                        583
                    ],
                    [
                        244,
                        587
                    ],
                    [
                        244,
                        588
                    ],
                    [
                        242,
                        590
                    ],
                    [
                        241,
                        590
                    ],
                    [
                        237,
                        594
                    ],
                    [
                        236,
                        594
                    ],
                    [
                        232,
                        598
                    ],
                    [
                        232,
                        599
                    ],
                    [
                        229,
                        602
                    ],
                    [
                        229,
                        603
                    ],
                    [
                        227,
                        605
                    ],
                    [
                        227,
                        606
                    ],
                    [
                        226,
                        607
                    ],
                    [
                        226,
                        608
                    ],
                    [
                        225,
                        609
                    ],
                    [
                        225,
                        610
                    ],
                    [
                        224,
                        611
                    ],
                    [
                        224,
                        612
                    ],
                    [
                        223,
                        613
                    ],
                    [
                        223,
                        614
                    ],
                    [
                        222,
                        615
                    ],
                    [
                        222,
                        616
                    ],
                    [
                        220,
                        618
                    ],
                    [
                        220,
                        619
                    ],
                    [
                        219,
                        620
                    ],
                    [
                        219,
                        621
                    ],
                    [
                        217,
                        623
                    ],
                    [
                        217,
                        624
                    ],
                    [
                        210,
                        631
                    ],
                    [
                        209,
                        631
                    ],
                    [
                        208,
                        632
                    ],
                    [
                        207,
                        632
                    ],
                    [
                        206,
                        633
                    ],
                    [
                        205,
                        633
                    ],
                    [
                        203,
                        635
                    ],
                    [
                        202,
                        635
                    ],
                    [
                        201,
                        636
                    ],
                    [
                        200,
                        636
                    ],
                    [
                        198,
                        638
                    ],
                    [
                        197,
                        638
                    ],
                    [
                        195,
                        640
                    ],
                    [
                        194,
                        640
                    ],
                    [
                        191,
                        643
                    ],
                    [
                        190,
                        643
                    ],
                    [
                        187,
                        646
                    ],
                    [
                        186,
                        646
                    ],
                    [
                        183,
                        649
                    ],
                    [
                        182,
                        649
                    ],
                    [
                        180,
                        651
                    ],
                    [
                        179,
                        651
                    ],
                    [
                        178,
                        652
                    ],
                    [
                        177,
                        652
                    ],
                    [
                        176,
                        653
                    ],
                    [
                        175,
                        653
                    ],
                    [
                        174,
                        654
                    ],
                    [
                        173,
                        654
                    ],
                    [
                        172,
                        655
                    ],
                    [
                        171,
                        655
                    ],
                    [
                        170,
                        656
                    ],
                    [
                        169,
                        656
                    ],
                    [
                        168,
                        657
                    ],
                    [
                        167,
                        657
                    ],
                    [
                        166,
                        658
                    ],
                    [
                        164,
                        658
                    ],
                    [
                        163,
                        659
                    ],
                    [
                        162,
                        659
                    ],
                    [
                        161,
                        660
                    ],
                    [
                        160,
                        660
                    ],
                    [
                        159,
                        661
                    ],
                    [
                        157,
                        661
                    ],
                    [
                        156,
                        662
                    ],
                    [
                        155,
                        662
                    ],
                    [
                        154,
                        663
                    ],
                    [
                        152,
                        663
                    ],
                    [
                        151,
                        664
                    ],
                    [
                        148,
                        664
                    ],
                    [
                        147,
                        665
                    ],
                    [
                        146,
                        665
                    ],
                    [
                        145,
                        666
                    ],
                    [
                        143,
                        666
                    ],
                    [
                        142,
                        667
                    ],
                    [
                        141,
                        667
                    ],
                    [
                        140,
                        668
                    ],
                    [
                        138,
                        668
                    ],
                    [
                        137,
                        669
                    ],
                    [
                        136,
                        669
                    ],
                    [
                        135,
                        670
                    ],
                    [
                        133,
                        670
                    ],
                    [
                        132,
                        671
                    ],
                    [
                        131,
                        671
                    ],
                    [
                        130,
                        672
                    ],
                    [
                        127,
                        672
                    ],
                    [
                        126,
                        673
                    ],
                    [
                        95,
                        673
                    ],
                    [
                        94,
                        672
                    ],
                    [
                        92,
                        672
                    ],
                    [
                        91,
                        671
                    ],
                    [
                        89,
                        671
                    ],
                    [
                        88,
                        670
                    ],
                    [
                        87,
                        670
                    ],
                    [
                        86,
                        669
                    ],
                    [
                        85,
                        669
                    ],
                    [
                        84,
                        668
                    ],
                    [
                        82,
                        668
                    ],
                    [
                        81,
                        667
                    ],
                    [
                        80,
                        667
                    ],
                    [
                        79,
                        666
                    ],
                    [
                        78,
                        666
                    ],
                    [
                        77,
                        665
                    ],
                    [
                        75,
                        665
                    ],
                    [
                        74,
                        664
                    ],
                    [
                        72,
                        664
                    ],
                    [
                        71,
                        663
                    ],
                    [
                        70,
                        663
                    ],
                    [
                        69,
                        662
                    ],
                    [
                        68,
                        662
                    ],
                    [
                        67,
                        661
                    ],
                    [
                        66,
                        661
                    ],
                    [
                        65,
                        660
                    ],
                    [
                        63,
                        660
                    ],
                    [
                        63,
                        659
                    ],
                    [
                        62,
                        659
                    ],
                    [
                        60,
                        657
                    ],
                    [
                        59,
                        657
                    ],
                    [
                        56,
                        654
                    ],
                    [
                        54,
                        654
                    ],
                    [
                        42,
                        641
                    ],
                    [
                        41,
                        641
                    ],
                    [
                        34,
                        635
                    ],
                    [
                        34,
                        634
                    ],
                    [
                        32,
                        632
                    ],
                    [
                        32,
                        631
                    ],
                    [
                        31,
                        630
                    ],
                    [
                        31,
                        629
                    ],
                    [
                        30,
                        628
                    ],
                    [
                        30,
                        627
                    ],
                    [
                        29,
                        626
                    ],
                    [
                        29,
                        623
                    ],
                    [
                        28,
                        622
                    ],
                    [
                        28,
                        614
                    ],
                    [
                        27,
                        613
                    ],
                    [
                        27,
                        606
                    ],
                    [
                        26,
                        605
                    ],
                    [
                        26,
                        596
                    ],
                    [
                        25,
                        595
                    ],
                    [
                        25,
                        587
                    ],
                    [
                        24,
                        586
                    ],
                    [
                        24,
                        578
                    ],
                    [
                        23,
                        577
                    ],
                    [
                        23,
                        571
                    ],
                    [
                        22,
                        570
                    ],
                    [
                        22,
                        564
                    ],
                    [
                        21,
                        563
                    ],
                    [
                        21,
                        556
                    ],
                    [
                        20,
                        555
                    ],
                    [
                        20,
                        546
                    ],
                    [
                        19,
                        545
                    ],
                    [
                        19,
                        534
                    ],
                    [
                        18,
                        533
                    ],
                    [
                        18,
                        520
                    ],
                    [
                        17,
                        519
                    ],
                    [
                        17,
                        499
                    ],
                    [
                        16,
                        498
                    ],
                    [
                        17,
                        497
                    ],
                    [
                        17,
                        493
                    ],
                    [
                        18,
                        493
                    ],
                    [
                        18,
                        489
                    ],
                    [
                        19,
                        488
                    ],
                    [
                        19,
                        484
                    ],
                    [
                        20,
                        483
                    ],
                    [
                        20,
                        478
                    ],
                    [
                        21,
                        476
                    ],
                    [
                        21,
                        473
                    ],
                    [
                        22,
                        472
                    ],
                    [
                        22,
                        466
                    ],
                    [
                        23,
                        466
                    ],
                    [
                        23,
                        461
                    ],
                    [
                        24,
                        460
                    ],
                    [
                        24,
                        454
                    ],
                    [
                        25,
                        453
                    ],
                    [
                        25,
                        448
                    ],
                    [
                        26,
                        447
                    ],
                    [
                        26,
                        440
                    ],
                    [
                        27,
                        439
                    ],
                    [
                        27,
                        434
                    ],
                    [
                        28,
                        433
                    ],
                    [
                        28,
                        430
                    ],
                    [
                        29,
                        430
                    ],
                    [
                        29,
                        427
                    ],
                    [
                        30,
                        426
                    ],
                    [
                        30,
                        425
                    ],
                    [
                        31,
                        424
                    ],
                    [
                        31,
                        422
                    ],
                    [
                        32,
                        421
                    ],
                    [
                        32,
                        420
                    ],
                    [
                        33,
                        419
                    ],
                    [
                        33,
                        417
                    ],
                    [
                        34,
                        416
                    ],
                    [
                        34,
                        415
                    ],
                    [
                        36,
                        413
                    ],
                    [
                        36,
                        412
                    ],
                    [
                        41,
                        407
                    ],
                    [
                        42,
                        407
                    ],
                    [
                        50,
                        399
                    ],
                    [
                        50,
                        398
                    ],
                    [
                        52,
                        396
                    ],
                    [
                        52,
                        395
                    ],
                    [
                        53,
                        394
                    ],
                    [
                        53,
                        393
                    ],
                    [
                        54,
                        392
                    ],
                    [
                        54,
                        391
                    ],
                    [
                        56,
                        389
                    ],
                    [
                        56,
                        388
                    ],
                    [
                        57,
                        387
                    ],
                    [
                        57,
                        386
                    ],
                    [
                        67,
                        376
                    ],
                    [
                        68,
                        376
                    ],
                    [
                        70,
                        374
                    ],
                    [
                        71,
                        374
                    ],
                    [
                        77,
                        368
                    ],
                    [
                        77,
                        367
                    ],
                    [
                        78,
                        366
                    ],
                    [
                        78,
                        365
                    ],
                    [
                        79,
                        364
                    ],
                    [
                        79,
                        363
                    ],
                    [
                        80,
                        362
                    ],
                    [
                        80,
                        361
                    ],
                    [
                        81,
                        360
                    ],
                    [
                        81,
                        359
                    ],
                    [
                        82,
                        358
                    ],
                    [
                        82,
                        357
                    ],
                    [
                        83,
                        356
                    ],
                    [
                        83,
                        355
                    ],
                    [
                        84,
                        354
                    ],
                    [
                        84,
                        352
                    ],
                    [
                        85,
                        351
                    ],
                    [
                        85,
                        350
                    ],
                    [
                        86,
                        349
                    ],
                    [
                        86,
                        348
                    ],
                    [
                        87,
                        347
                    ],
                    [
                        87,
                        346
                    ],
                    [
                        96,
                        337
                    ],
                    [
                        97,
                        337
                    ],
                    [
                        99,
                        335
                    ],
                    [
                        100,
                        335
                    ],
                    [
                        106,
                        329
                    ],
                    [
                        106,
                        328
                    ],
                    [
                        107,
                        327
                    ],
                    [
                        107,
                        326
                    ],
                    [
                        108,
                        325
                    ],
                    [
                        108,
                        324
                    ],
                    [
                        109,
                        323
                    ],
                    [
                        109,
                        322
                    ],
                    [
                        110,
                        321
                    ],
                    [
                        110,
                        320
                    ],
                    [
                        111,
                        319
                    ],
                    [
                        111,
                        318
                    ],
                    [
                        112,
                        317
                    ],
                    [
                        112,
                        316
                    ],
                    [
                        113,
                        315
                    ],
                    [
                        113,
                        314
                    ],
                    [
                        114,
                        313
                    ],
                    [
                        114,
                        312
                    ],
                    [
                        115,
                        311
                    ],
                    [
                        115,
                        310
                    ],
                    [
                        116,
                        309
                    ],
                    [
                        116,
                        308
                    ],
                    [
                        118,
                        306
                    ],
                    [
                        118,
                        305
                    ],
                    [
                        125,
                        298
                    ],
                    [
                        126,
                        298
                    ],
                    [
                        131,
                        293
                    ],
                    [
                        131,
                        292
                    ],
                    [
                        134,
                        289
                    ],
                    [
                        134,
                        288
                    ],
                    [
                        136,
                        286
                    ],
                    [
                        136,
                        285
                    ],
                    [
                        137,
                        284
                    ],
                    [
                        137,
                        283
                    ],
                    [
                        138,
                        282
                    ],
                    [
                        138,
                        281
                    ],
                    [
                        139,
                        280
                    ],
                    [
                        139,
                        279
                    ],
                    [
                        140,
                        278
                    ],
                    [
                        140,
                        277
                    ],
                    [
                        142,
                        275
                    ],
                    [
                        142,
                        274
                    ],
                    [
                        144,
                        272
                    ],
                    [
                        144,
                        271
                    ],
                    [
                        162,
                        253
                    ],
                    [
                        162,
                        252
                    ],
                    [
                        167,
                        246
                    ],
                    [
                        167,
                        246
                    ],
                    [
                        170,
                        242
                    ],
                    [
                        170,
                        242
                    ],
                    [
                        175,
                        237
                    ],
                    [
                        176,
                        237
                    ],
                    [
                        178,
                        235
                    ],
                    [
                        179,
                        235
                    ],
                    [
                        180,
                        234
                    ],
                    [
                        181,
                        234
                    ],
                    [
                        182,
                        233
                    ],
                    [
                        184,
                        233
                    ],
                    [
                        185,
                        232
                    ],
                    [
                        186,
                        232
                    ],
                    [
                        187,
                        231
                    ],
                    [
                        189,
                        231
                    ],
                    [
                        190,
                        230
                    ],
                    [
                        191,
                        230
                    ],
                    [
                        192,
                        229
                    ],
                    [
                        194,
                        229
                    ],
                    [
                        195,
                        228
                    ],
                    [
                        196,
                        228
                    ],
                    [
                        197,
                        227
                    ],
                    [
                        198,
                        227
                    ],
                    [
                        199,
                        226
                    ],
                    [
                        200,
                        226
                    ],
                    [
                        201,
                        225
                    ],
                    [
                        203,
                        225
                    ],
                    [
                        204,
                        224
                    ],
                    [
                        205,
                        224
                    ],
                    [
                        206,
                        223
                    ],
                    [
                        207,
                        223
                    ],
                    [
                        208,
                        222
                    ],
                    [
                        209,
                        222
                    ],
                    [
                        210,
                        221
                    ],
                    [
                        211,
                        221
                    ],
                    [
                        212,
                        220
                    ],
                    [
                        213,
                        220
                    ],
                    [
                        214,
                        219
                    ],
                    [
                        215,
                        219
                    ],
                    [
                        215,
                        218
                    ],
                    [
                        217,
                        218
                    ],
                    [
                        218,
                        217
                    ],
                    [
                        219,
                        217
                    ],
                    [
                        219,
                        216
                    ],
                    [
                        221,
                        216
                    ],
                    [
                        222,
                        215
                    ],
                    [
                        224,
                        215
                    ],
                    [
                        224,
                        214
                    ],
                    [
                        227,
                        214
                    ],
                    [
                        228,
                        213
                    ],
                    [
                        230,
                        213
                    ],
                    [
                        231,
                        212
                    ],
                    [
                        233,
                        212
                    ],
                    [
                        233,
                        211
                    ],
                    [
                        237,
                        211
                    ],
                    [
                        239,
                        210
                    ],
                    [
                        242,
                        210
                    ],
                    [
                        242,
                        209
                    ],
                    [
                        246,
                        209
                    ],
                    [
                        246,
                        208
                    ],
                    [
                        250,
                        208
                    ],
                    [
                        251,
                        207
                    ],
                    [
                        254,
                        207
                    ],
                    [
                        255,
                        206
                    ],
                    [
                        257,
                        206
                    ],
                    [
                        258,
                        205
                    ],
                    [
                        261,
                        205
                    ],
                    [
                        262,
                        204
                    ],
                    [
                        264,
                        204
                    ],
                    [
                        265,
                        203
                    ],
                    [
                        266,
                        203
                    ],
                    [
                        267,
                        202
                    ],
                    [
                        268,
                        202
                    ],
                    [
                        269,
                        201
                    ],
                    [
                        270,
                        201
                    ],
                    [
                        272,
                        199
                    ],
                    [
                        273,
                        199
                    ],
                    [
                        277,
                        195
                    ],
                    [
                        278,
                        195
                    ],
                    [
                        280,
                        193
                    ],
                    [
                        281,
                        193
                    ],
                    [
                        282,
                        192
                    ],
                    [
                        283,
                        192
                    ],
                    [
                        284,
                        191
                    ],
                    [
                        285,
                        191
                    ],
                    [
                        286,
                        190
                    ],
                    [
                        288,
                        190
                    ],
                    [
                        289,
                        189
                    ],
                    [
                        290,
                        189
                    ],
                    [
                        291,
                        188
                    ],
                    [
                        293,
                        188
                    ],
                    [
                        294,
                        187
                    ],
                    [
                        295,
                        187
                    ],
                    [
                        296,
                        186
                    ],
                    [
                        297,
                        186
                    ],
                    [
                        298,
                        185
                    ],
                    [
                        299,
                        185
                    ],
                    [
                        300,
                        184
                    ],
                    [
                        301,
                        184
                    ],
                    [
                        302,
                        183
                    ],
                    [
                        303,
                        183
                    ],
                    [
                        305,
                        181
                    ],
                    [
                        306,
                        181
                    ],
                    [
                        311,
                        176
                    ],
                    [
                        312,
                        176
                    ],
                    [
                        314,
                        174
                    ],
                    [
                        315,
                        174
                    ],
                    [
                        317,
                        172
                    ],
                    [
                        318,
                        172
                    ],
                    [
                        319,
                        171
                    ],
                    [
                        321,
                        171
                    ],
                    [
                        322,
                        170
                    ],
                    [
                        326,
                        170
                    ],
                    [
                        327,
                        169
                    ],
                    [
                        332,
                        169
                    ],
                    [
                        333,
                        168
                    ],
                    [
                        339,
                        168
                    ],
                    [
                        340,
                        167
                    ],
                    [
                        346,
                        167
                    ],
                    [
                        347,
                        166
                    ],
                    [
                        489,
                        166
                    ],
                    [
                        490,
                        167
                    ],
                    [
                        498,
                        167
                    ],
                    [
                        499,
                        168
                    ],
                    [
                        506,
                        168
                    ],
                    [
                        507,
                        169
                    ],
                    [
                        513,
                        169
                    ],
                    [
                        514,
                        170
                    ],
                    [
                        516,
                        170
                    ],
                    [
                        517,
                        171
                    ],
                    [
                        518,
                        171
                    ],
                    [
                        519,
                        172
                    ],
                    [
                        520,
                        172
                    ],
                    [
                        522,
                        174
                    ],
                    [
                        523,
                        174
                    ],
                    [
                        525,
                        176
                    ],
                    [
                        526,
                        176
                    ],
                    [
                        531,
                        181
                    ],
                    [
                        532,
                        181
                    ],
                    [
                        533,
                        182
                    ],
                    [
                        534,
                        182
                    ],
                    [
                        535,
                        183
                    ],
                    [
                        536,
                        183
                    ],
                    [
                        537,
                        184
                    ],
                    [
                        538,
                        184
                    ],
                    [
                        539,
                        185
                    ],
                    [
                        540,
                        185
                    ],
                    [
                        541,
                        186
                    ],
                    [
                        543,
                        186
                    ],
                    [
                        544,
                        187
                    ],
                    [
                        545,
                        187
                    ],
                    [
                        546,
                        188
                    ],
                    [
                        547,
                        188
                    ],
                    [
                        548,
                        189
                    ],
                    [
                        549,
                        189
                    ],
                    [
                        550,
                        190
                    ],
                    [
                        551,
                        190
                    ],
                    [
                        553,
                        192
                    ],
                    [
                        554,
                        192
                    ],
                    [
                        564,
                        202
                    ],
                    [
                        565,
                        202
                    ],
                    [
                        567,
                        204
                    ],
                    [
                        568,
                        204
                    ],
                    [
                        569,
                        205
                    ],
                    [
                        570,
                        205
                    ],
                    [
                        571,
                        206
                    ],
                    [
                        572,
                        206
                    ],
                    [
                        573,
                        207
                    ],
                    [
                        574,
                        207
                    ],
                    [
                        575,
                        208
                    ],
                    [
                        576,
                        208
                    ],
                    [
                        577,
                        209
                    ],
                    [
                        578,
                        209
                    ],
                    [
                        580,
                        211
                    ],
                    [
                        581,
                        211
                    ],
                    [
                        585,
                        215
                    ],
                    [
                        586,
                        215
                    ],
                    [
                        588,
                        218
                    ],
                    [
                        588,
                        219
                    ],
                    [
                        593,
                        223
                    ],
                    [
                        594,
                        223
                    ],
                    [
                        596,
                        225
                    ],
                    [
                        597,
                        225
                    ],
                    [
                        599,
                        227
                    ],
                    [
                        600,
                        227
                    ],
                    [
                        601,
                        228
                    ],
                    [
                        602,
                        228
                    ],
                    [
                        605,
                        231
                    ],
                    [
                        606,
                        231
                    ],
                    [
                        611,
                        237
                    ],
                    [
                        611,
                        237
                    ],
                    [
                        614,
                        241
                    ],
                    [
                        614,
                        242
                    ],
                    [
                        622,
                        249
                    ],
                    [
                        623,
                        249
                    ],
                    [
                        625,
                        251
                    ],
                    [
                        626,
                        251
                    ],
                    [
                        627,
                        252
                    ],
                    [
                        628,
                        252
                    ],
                    [
                        630,
                        254
                    ],
                    [
                        631,
                        254
                    ],
                    [
                        638,
                        262
                    ],
                    [
                        638,
                        263
                    ],
                    [
                        640,
                        265
                    ],
                    [
                        640,
                        266
                    ],
                    [
                        642,
                        268
                    ],
                    [
                        642,
                        269
                    ],
                    [
                        645,
                        272
                    ],
                    [
                        645,
                        273
                    ],
                    [
                        651,
                        278
                    ],
                    [
                        652,
                        278
                    ],
                    [
                        660,
                        287
                    ],
                    [
                        660,
                        288
                    ],
                    [
                        662,
                        290
                    ],
                    [
                        662,
                        291
                    ],
                    [
                        664,
                        293
                    ],
                    [
                        664,
                        294
                    ],
                    [
                        665,
                        295
                    ],
                    [
                        665,
                        296
                    ],
                    [
                        666,
                        297
                    ],
                    [
                        666,
                        298
                    ],
                    [
                        668,
                        300
                    ],
                    [
                        668,
                        301
                    ],
                    [
                        669,
                        302
                    ],
                    [
                        669,
                        303
                    ],
                    [
                        670,
                        304
                    ],
                    [
                        670,
                        305
                    ],
                    [
                        671,
                        306
                    ],
                    [
                        671,
                        307
                    ],
                    [
                        681,
                        316
                    ],
                    [
                        682,
                        316
                    ],
                    [
                        691,
                        326
                    ],
                    [
                        691,
                        327
                    ],
                    [
                        692,
                        328
                    ],
                    [
                        692,
                        329
                    ],
                    [
                        693,
                        330
                    ],
                    [
                        693,
                        331
                    ],
                    [
                        694,
                        332
                    ],
                    [
                        694,
                        334
                    ],
                    [
                        695,
                        335
                    ],
                    [
                        695,
                        336
                    ],
                    [
                        696,
                        337
                    ],
                    [
                        696,
                        338
                    ],
                    [
                        697,
                        339
                    ],
                    [
                        697,
                        340
                    ],
                    [
                        698,
                        341
                    ],
                    [
                        698,
                        342
                    ],
                    [
                        699,
                        343
                    ],
                    [
                        699,
                        344
                    ],
                    [
                        700,
                        345
                    ],
                    [
                        700,
                        346
                    ],
                    [
                        701,
                        347
                    ],
                    [
                        701,
                        348
                    ],
                    [
                        708,
                        354
                    ],
                    [
                        709,
                        354
                    ],
                    [
                        711,
                        356
                    ],
                    [
                        712,
                        356
                    ],
                    [
                        719,
                        364
                    ],
                    [
                        719,
                        365
                    ],
                    [
                        721,
                        367
                    ],
                    [
                        721,
                        368
                    ],
                    [
                        722,
                        369
                    ],
                    [
                        722,
                        370
                    ],
                    [
                        723,
                        371
                    ],
                    [
                        723,
                        372
                    ],
                    [
                        724,
                        373
                    ],
                    [
                        724,
                        375
                    ],
                    [
                        725,
                        376
                    ],
                    [
                        725,
                        377
                    ],
                    [
                        726,
                        378
                    ],
                    [
                        726,
                        380
                    ],
                    [
                        727,
                        381
                    ],
                    [
                        727,
                        382
                    ],
                    [
                        728,
                        383
                    ],
                    [
                        728,
                        384
                    ],
                    [
                        729,
                        385
                    ],
                    [
                        729,
                        386
                    ],
                    [
                        730,
                        387
                    ],
                    [
                        730,
                        388
                    ],
                    [
                        731,
                        389
                    ],
                    [
                        731,
                        390
                    ],
                    [
                        732,
                        391
                    ],
                    [
                        732,
                        392
                    ],
                    [
                        733,
                        393
                    ],
                    [
                        733,
                        394
                    ],
                    [
                        734,
                        395
                    ],
                    [
                        734,
                        396
                    ],
                    [
                        736,
                        398
                    ],
                    [
                        736,
                        399
                    ],
                    [
                        738,
                        401
                    ],
                    [
                        738,
                        402
                    ],
                    [
                        739,
                        403
                    ],
                    [
                        739,
                        404
                    ],
                    [
                        741,
                        406
                    ],
                    [
                        741,
                        407
                    ],
                    [
                        742,
                        408
                    ],
                    [
                        742,
                        410
                    ],
                    [
                        743,
                        411
                    ],
                    [
                        743,
                        412
                    ],
                    [
                        744,
                        413
                    ],
                    [
                        744,
                        416
                    ],
                    [
                        745,
                        417
                    ],
                    [
                        745,
                        421
                    ],
                    [
                        746,
                        422
                    ],
                    [
                        746,
                        426
                    ],
                    [
                        747,
                        427
                    ],
                    [
                        747,
                        430
                    ],
                    [
                        748,
                        431
                    ],
                    [
                        748,
                        439
                    ],
                    [
                        749,
                        440
                    ],
                    [
                        749,
                        451
                    ],
                    [
                        750,
                        452
                    ],
                    [
                        750,
                        466
                    ],
                    [
                        751,
                        466
                    ],
                    [
                        751,
                        483
                    ],
                    [
                        752,
                        484
                    ],
                    [
                        752,
                        499
                    ],
                    [
                        753,
                        500
                    ],
                    [
                        753,
                        513
                    ],
                    [
                        754,
                        514
                    ],
                    [
                        754,
                        526
                    ],
                    [
                        755,
                        527
                    ],
                    [
                        755,
                        538
                    ],
                    [
                        756,
                        539
                    ],
                    [
                        756,
                        550
                    ],
                    [
                        757,
                        551
                    ],
                    [
                        757,
                        560
                    ],
                    [
                        758,
                        561
                    ],
                    [
                        758,
                        569
                    ],
                    [
                        759,
                        570
                    ],
                    [
                        759,
                        577
                    ],
                    [
                        760,
                        578
                    ],
                    [
                        760,
                        585
                    ],
                    [
                        761,
                        586
                    ],
                    [
                        761,
                        593
                    ],
                    [
                        762,
                        594
                    ],
                    [
                        762,
                        601
                    ],
                    [
                        763,
                        602
                    ],
                    [
                        763,
                        624
                    ],
                    [
                        762,
                        625
                    ],
                    [
                        762,
                        635
                    ],
                    [
                        761,
                        636
                    ],
                    [
                        761,
                        646
                    ],
                    [
                        760,
                        647
                    ],
                    [
                        760,
                        654
                    ],
                    [
                        759,
                        655
                    ],
                    [
                        759,
                        663
                    ],
                    [
                        758,
                        664
                    ],
                    [
                        758,
                        670
                    ],
                    [
                        757,
                        671
                    ],
                    [
                        757,
                        674
                    ],
                    [
                        756,
                        675
                    ],
                    [
                        756,
                        679
                    ],
                    [
                        755,
                        680
                    ],
                    [
                        755,
                        685
                    ],
                    [
                        754,
                        686
                    ],
                    [
                        754,
                        691
                    ],
                    [
                        753,
                        692
                    ],
                    [
                        753,
                        699
                    ],
                    [
                        752,
                        700
                    ],
                    [
                        752,
                        707
                    ],
                    [
                        751,
                        708
                    ],
                    [
                        751,
                        713
                    ],
                    [
                        750,
                        714
                    ],
                    [
                        750,
                        716
                    ],
                    [
                        749,
                        717
                    ],
                    [
                        749,
                        720
                    ],
                    [
                        748,
                        721
                    ],
                    [
                        748,
                        723
                    ],
                    [
                        747,
                        724
                    ],
                    [
                        747,
                        726
                    ],
                    [
                        746,
                        727
                    ],
                    [
                        746,
                        728
                    ],
                    [
                        745,
                        729
                    ],
                    [
                        745,
                        731
                    ],
                    [
                        744,
                        732
                    ],
                    [
                        744,
                        733
                    ],
                    [
                        743,
                        734
                    ],
                    [
                        743,
                        735
                    ],
                    [
                        742,
                        736
                    ],
                    [
                        742,
                        738
                    ],
                    [
                        741,
                        739
                    ],
                    [
                        741,
                        740
                    ],
                    [
                        740,
                        741
                    ],
                    [
                        740,
                        742
                    ],
                    [
                        739,
                        743
                    ],
                    [
                        739,
                        744
                    ],
                    [
                        738,
                        745
                    ],
                    [
                        738,
                        746
                    ],
                    [
                        736,
                        748
                    ],
                    [
                        736,
                        749
                    ],
                    [
                        734,
                        751
                    ],
                    [
                        734,
                        752
                    ],
                    [
                        733,
                        753
                    ],
                    [
                        733,
                        754
                    ],
                    [
                        733,
                        754
                    ],
                    [
                        732,
                        754
                    ],
                    [
                        731,
                        755
                    ],
                    [
                        730,
                        755
                    ],
                    [
                        729,
                        756
                    ],
                    [
                        728,
                        756
                    ],
                    [
                        727,
                        757
                    ],
                    [
                        726,
                        757
                    ],
                    [
                        725,
                        758
                    ],
                    [
                        724,
                        758
                    ],
                    [
                        723,
                        759
                    ],
                    [
                        721,
                        759
                    ],
                    [
                        720,
                        760
                    ],
                    [
                        718,
                        760
                    ],
                    [
                        717,
                        761
                    ],
                    [
                        714,
                        761
                    ],
                    [
                        713,
                        762
                    ],
                    [
                        710,
                        762
                    ],
                    [
                        709,
                        763
                    ],
                    [
                        678,
                        763
                    ]
                ],
                "interior": []
            }
        }
    ]
}