{
    "description": "",
    "tags": [],
    "size": {
        "height": 852,
        "width": 852
    },
    "objects": [
        {
            "id": 1646088,
            "classId": 3877,
            "description": "",
            "geometryType": "polygon",
            "labelerLogin": "az@datasetninja.com",
            "createdAt": "2023-06-07T13:07:03.820Z",
            "updatedAt": "2023-06-07T13:07:03.820Z",
            "tags": [],
            "classTitle": "mixed-salad-chopped-without-sauce",
            "points": {
                "exterior": [
                    [
                        738,
                        728
                    ],
                    [
                        810,
                        656
                    ],
                    [
                        808,
                        500
                    ],
                    [
                        769,
                        391
                    ],
                    [
                        761,
                        293
                    ],
                    [
                        711,
                        296
                    ],
                    [
                        641,
                        211
                    ],
                    [
                        562,
                        155
                    ],
                    [
                        438,
                        151
                    ],
                    [
                        376,
                        183
                    ],
                    [
                        323,
                        238
                    ],
                    [
                        268,
                        353
                    ],
                    [
                        208,
                        402
                    ],
                    [
                        238,
                        530
                    ],
                    [
                        278,
                        620
                    ],
                    [
                        372,
                        637
                    ],
                    [
                        434,
                        652
                    ],
                    [
                        477,
                        686
                    ],
                    [
                        568,
                        730
                    ],
                    [
                        632,
                        730
                    ],
                    [
                        653,
                        703
                    ],
                    [
                        662,
                        698
                    ],
                    [
                        664,
                        698
                    ]
                ],
                "interior": []
            }
        },
        {
            "id": 1646086,
            "classId": 3871,
            "description": "",
            "geometryType": "polygon",
            "labelerLogin": "az@datasetninja.com",
            "createdAt": "2023-06-07T13:07:03.819Z",
            "updatedAt": "2023-06-07T13:07:03.819Z",
            "tags": [],
            "classTitle": "salad-dressing",
            "points": {
                "exterior": [
                    [
                        169,
                        227
                    ],
                    [
                        137,
                        227
                    ],
                    [
                        110,
                        223
                    ],
                    [
                        91,
                        213
                    ],
                    [
                        77,
                        199
                    ],
                    [
                        69,
                        170
                    ],
                    [
                        70,
                        123
                    ],
                    [
                        76,
                        111
                    ],
                    [
                        100,
                        89
                    ],
                    [
                        138,
                        61
                    ],
                    [
                        162,
                        50
                    ],
                    [
                        262,
                        34
                    ],
                    [
                        308,
                        38
                    ],
                    [
                        339,
                        50
                    ],
                    [
                        345,
                        56
                    ],
                    [
                        350,
                        69
                    ],
                    [
                        349,
                        97
                    ],
                    [
                        341,
                        126
                    ],
                    [
                        321,
                        157
                    ],
                    [
                        288,
                        182
                    ],
                    [
                        235,
                        212
                    ],
                    [
                        200,
                        223
                    ]
                ],
                "interior": []
            }
        },
        {
            "id": 1646084,
            "classId": 3617,
            "description": "",
            "geometryType": "polygon",
            "labelerLogin": "az@datasetninja.com",
            "createdAt": "2023-06-07T13:07:03.819Z",
            "updatedAt": "2023-06-07T13:07:03.819Z",
            "tags": [],
            "classTitle": "bread-white",
            "points": {
                "exterior": [
                    [
                        136,
                        770
                    ],
                    [
                        104,
                        766
                    ],
                    [
                        68,
                        750
                    ],
                    [
                        33,
                        744
                    ],
                    [
                        22,
                        738
                    ],
                    [
                        13,
                        716
                    ],
                    [
                        12,
                        627
                    ],
                    [
                        14,
                        610
                    ],
                    [
                        22,
                        587
                    ],
                    [
                        42,
                        556
                    ],
                    [
                        105,
                        499
                    ],
                    [
                        123,
                        488
                    ],
                    [
                        146,
                        485
                    ],
                    [
                        170,
                        491
                    ],
                    [
                        195,
                        511
                    ],
                    [
                        213,
                        535
                    ],
                    [
                        224,
                        563
                    ],
                    [
                        268,
                        649
                    ],
                    [
                        275,
                        697
                    ],
                    [
                        268,
                        714
                    ],
                    [
                        255,
                        723
                    ],
                    [
                        171,
                        762
                    ]
                ],
                "interior": []
            }
        }
    ]
}