{
    "description": "",
    "tags": [],
    "size": {
        "height": 480,
        "width": 480
    },
    "objects": [
        {
            "id": 1807047,
            "classId": 3543,
            "description": "",
            "geometryType": "polygon",
            "labelerLogin": "az@datasetninja.com",
            "createdAt": "2023-06-07T14:58:06.759Z",
            "updatedAt": "2023-06-07T14:58:06.759Z",
            "tags": [],
            "classTitle": "rice",
            "points": {
                "exterior": [
                    [
                        281,
                        432
                    ],
                    [
                        262,
                        432
                    ],
                    [
                        241,
                        423
                    ],
                    [
                        234,
                        418
                    ],
                    [
                        228,
                        405
                    ],
                    [
                        229,
                        373
                    ],
                    [
                        221,
                        331
                    ],
                    [
                        220,
                        303
                    ],
                    [
                        234,
                        253
                    ],
                    [
                        236,
                        227
                    ],
                    [
                        226,
                        183
                    ],
                    [
                        227,
                        150
                    ],
                    [
                        242,
                        122
                    ],
                    [
                        257,
                        107
                    ],
                    [
                        271,
                        101
                    ],
                    [
                        280,
                        92
                    ],
                    [
                        308,
                        85
                    ],
                    [
                        329,
                        86
                    ],
                    [
                        359,
                        93
                    ],
                    [
                        377,
                        106
                    ],
                    [
                        397,
                        139
                    ],
                    [
                        421,
                        161
                    ],
                    [
                        431,
                        175
                    ],
                    [
                        444,
                        213
                    ],
                    [
                        453,
                        226
                    ],
                    [
                        457,
                        237
                    ],
                    [
                        457,
                        252
                    ],
                    [
                        435,
                        274
                    ],
                    [
                        425,
                        293
                    ],
                    [
                        414,
                        327
                    ],
                    [
                        412,
                        373
                    ],
                    [
                        403,
                        391
                    ],
                    [
                        398,
                        396
                    ],
                    [
                        387,
                        400
                    ],
                    [
                        378,
                        400
                    ],
                    [
                        364,
                        394
                    ],
                    [
                        348,
                        395
                    ],
                    [
                        333,
                        403
                    ],
                    [
                        301,
                        430
                    ]
                ],
                "interior": []
            }
        }
    ]
}