{
    "description": "",
    "tags": [],
    "size": {
        "height": 391,
        "width": 392
    },
    "objects": [
        {
            "id": 1781870,
            "classId": 4233,
            "description": "",
            "geometryType": "polygon",
            "labelerLogin": "az@datasetninja.com",
            "createdAt": "2023-06-07T14:40:49.572Z",
            "updatedAt": "2023-06-07T14:40:49.572Z",
            "tags": [],
            "classTitle": "muffin",
            "points": {
                "exterior": [
                    [
                        206,
                        354
                    ],
                    [
                        138,
                        353
                    ],
                    [
                        103,
                        342
                    ],
                    [
                        66,
                        309
                    ],
                    [
                        52,
                        290
                    ],
                    [
                        42,
                        269
                    ],
                    [
                        27,
                        214
                    ],
                    [
                        28,
                        166
                    ],
                    [
                        38,
                        149
                    ],
                    [
                        42,
                        135
                    ],
                    [
                        63,
                        107
                    ],
                    [
                        79,
                        93
                    ],
                    [
                        105,
                        81
                    ],
                    [
                        196,
                        73
                    ],
                    [
                        219,
                        74
                    ],
                    [
                        250,
                        81
                    ],
                    [
                        268,
                        92
                    ],
                    [
                        289,
                        114
                    ],
                    [
                        303,
                        147
                    ],
                    [
                        324,
                        178
                    ],
                    [
                        327,
                        214
                    ],
                    [
                        323,
                        248
                    ],
                    [
                        329,
                        258
                    ],
                    [
                        343,
                        266
                    ],
                    [
                        348,
                        274
                    ],
                    [
                        347,
                        300
                    ],
                    [
                        329,
                        312
                    ],
                    [
                        282,
                        326
                    ],
                    [
                        226,
                        351
                    ]
                ],
                "interior": []
            }
        }
    ]
}