{
    "description": "",
    "tags": [],
    "size": {
        "height": 390,
        "width": 391
    },
    "objects": [
        {
            "id": 1706783,
            "classId": 3463,
            "description": "",
            "geometryType": "polygon",
            "labelerLogin": "az@datasetninja.com",
            "createdAt": "2023-06-07T13:48:42.088Z",
            "updatedAt": "2023-06-07T13:48:42.088Z",
            "tags": [],
            "classTitle": "tomato-raw",
            "points": {
                "exterior": [
                    [
                        194,
                        170
                    ],
                    [
                        190,
                        142
                    ],
                    [
                        181,
                        120
                    ],
                    [
                        171,
                        101
                    ],
                    [
                        135,
                        73
                    ],
                    [
                        119,
                        89
                    ],
                    [
                        92,
                        81
                    ],
                    [
                        79,
                        109
                    ],
                    [
                        76,
                        136
                    ],
                    [
                        62,
                        154
                    ],
                    [
                        52,
                        168
                    ],
                    [
                        71,
                        179
                    ],
                    [
                        91,
                        148
                    ],
                    [
                        126,
                        163
                    ],
                    [
                        161,
                        163
                    ]
                ],
                "interior": []
            }
        },
        {
            "id": 1706781,
            "classId": 3453,
            "description": "",
            "geometryType": "polygon",
            "labelerLogin": "az@datasetninja.com",
            "createdAt": "2023-06-07T13:48:42.087Z",
            "updatedAt": "2023-06-07T13:48:42.087Z",
            "tags": [],
            "classTitle": "egg",
            "points": {
                "exterior": [
                    [
                        300,
                        194
                    ],
                    [
                        203,
                        196
                    ],
                    [
                        164,
                        177
                    ],
                    [
                        87,
                        168
                    ],
                    [
                        65,
                        196
                    ],
                    [
                        47,
                        191
                    ],
                    [
                        30,
                        215
                    ],
                    [
                        7,
                        251
                    ],
                    [
                        27,
                        273
                    ],
                    [
                        60,
                        295
                    ],
                    [
                        138,
                        345
                    ],
                    [
                        183,
                        322
                    ],
                    [
                        250,
                        339
                    ],
                    [
                        333,
                        318
                    ],
                    [
                        366,
                        270
                    ],
                    [
                        367,
                        223
                    ],
                    [
                        324,
                        200
                    ]
                ],
                "interior": []
            }
        },
        {
            "id": 1706779,
            "classId": 3445,
            "description": "",
            "geometryType": "polygon",
            "labelerLogin": "az@datasetninja.com",
            "createdAt": "2023-06-07T13:48:42.086Z",
            "updatedAt": "2023-06-07T13:48:42.086Z",
            "tags": [],
            "classTitle": "avocado",
            "points": {
                "exterior": [
                    [
                        185,
                        120
                    ],
                    [
                        191,
                        77
                    ],
                    [
                        209,
                        64
                    ],
                    [
                        244,
                        61
                    ],
                    [
                        269,
                        81
                    ],
                    [
                        275,
                        90
                    ],
                    [
                        294,
                        98
                    ],
                    [
                        300,
                        108
                    ],
                    [
                        319,
                        142
                    ],
                    [
                        318,
                        151
                    ],
                    [
                        304,
                        184
                    ],
                    [
                        284,
                        185
                    ],
                    [
                        269,
                        184
                    ],
                    [
                        248,
                        162
                    ],
                    [
                        242,
                        145
                    ],
                    [
                        229,
                        144
                    ],
                    [
                        218,
                        144
                    ],
                    [
                        218,
                        144
                    ]
                ],
                "interior": []
            }
        }
    ]
}