{
    "description": "",
    "tags": [],
    "size": {
        "height": 1024,
        "width": 1024
    },
    "objects": [
        {
            "id": 1675950,
            "classId": 3523,
            "description": "",
            "geometryType": "polygon",
            "labelerLogin": "az@datasetninja.com",
            "createdAt": "2023-06-07T13:27:14.916Z",
            "updatedAt": "2023-06-07T13:27:14.916Z",
            "tags": [],
            "classTitle": "wine-red",
            "points": {
                "exterior": [
                    [
                        523,
                        534
                    ],
                    [
                        523,
                        534
                    ],
                    [
                        452,
                        533
                    ],
                    [
                        415,
                        511
                    ],
                    [
                        390,
                        488
                    ],
                    [
                        350,
                        425
                    ],
                    [
                        344,
                        395
                    ],
                    [
                        343,
                        370
                    ],
                    [
                        350,
                        348
                    ],
                    [
                        359,
                        339
                    ],
                    [
                        391,
                        318
                    ],
                    [
                        441,
                        295
                    ],
                    [
                        497,
                        286
                    ],
                    [
                        573,
                        294
                    ],
                    [
                        612,
                        307
                    ],
                    [
                        657,
                        337
                    ],
                    [
                        670,
                        367
                    ],
                    [
                        670,
                        405
                    ],
                    [
                        657,
                        439
                    ],
                    [
                        638,
                        463
                    ],
                    [
                        631,
                        478
                    ],
                    [
                        606,
                        507
                    ],
                    [
                        585,
                        523
                    ]
                ],
                "interior": []
            }
        }
    ]
}